setup.py
distributions_noemi/Binomialdistribution.py
distributions_noemi/Gaussiandistribution.py
distributions_noemi/Generaldistribution.py
distributions_noemi/__init__.py
distributions_noemi.egg-info/PKG-INFO
distributions_noemi.egg-info/SOURCES.txt
distributions_noemi.egg-info/dependency_links.txt
distributions_noemi.egg-info/not-zip-safe
distributions_noemi.egg-info/top_level.txt